core_xlsx-0.12.4.dist-info/METADATA
core_xlsx-0.12.4.dist-info/WHEEL
core_xlsx/_core_xlsx.pyi
core_xlsx/__init__.py
core_xlsx/py.typed
core_xlsx/_core_xlsx.cpython-313-x86_64-linux-gnu.so
core_xlsx-0.12.4.dist-info/RECORD
