Metadata-Version: 2.4
Name: core_xlsx
Version: 0.12.4
Classifier: Programming Language :: Rust
Classifier: Programming Language :: Python :: Implementation :: CPython
Classifier: Programming Language :: Python :: Implementation :: PyPy
Classifier: Programming Language :: Python :: 3.12
Classifier: Operating System :: POSIX :: Linux
Classifier: Operating System :: MacOS
Summary: Core functionality for XLSX
Home-Page: https://github.com/stalexsm/core_xlsx.git
Author: Alexander Starovoytov
Author-email: stalex.info@yandex.ru
Requires-Python: >=3.12
Project-URL: Source Code, https://github.com/stalexsm/core_xlsx.git
